shuttlet_nano_banana_mcp/__init__.py
shuttlet_nano_banana_mcp-0.1.4.dist-info/WHEEL
shuttlet_nano_banana_mcp-0.1.4.dist-info/entry_points.txt
shuttlet_nano_banana_mcp-0.1.4.dist-info/METADATA
shuttlet_nano_banana_mcp-0.1.4.dist-info/RECORD
