Metadata-Version: 2.3
Name: shuttlet_nano_banana_mcp
Version: 0.1.4
Summary: Nano-Banana MCP Server - 基于 gemini-2.5-flash-image-preview 的画图 API
Author: entelin
Author-email: entelin <entelin@tencent.com>
Requires-Dist: mcp[cli]>=1.25.0
Requires-Dist: requests>=2.32.5
Requires-Python: >=3.13
